shadeorb/__init__.py
shadeorb/const.py
shadeorb/exceptions.py
shadeorb/models.py
shadeorb/orb.py
shadeorb/protocol.py
shadeorb-0.0.3.dist-info/LICENSE
shadeorb-0.0.3.dist-info/METADATA
shadeorb-0.0.3.dist-info/WHEEL
shadeorb-0.0.3.dist-info/RECORD
