Metadata-Version: 2.1
Name: shadeorb
Version: 0.0.3
Summary: Package to control Shade ORB lights
Home-page: https://github.com/blitzkopf/shadeorb
License: MIT
Keywords: shadeorb,lights,bleak,bluetooth,homeassistant
Author: Yngvi Thor Sigurjonsson
Author-email: blitzkopf@gmail.com
Requires-Python: >=3.10,<3.13
Classifier: Development Status :: 2 - Pre-Alpha
Classifier: License :: OSI Approved :: MIT License
Classifier: Programming Language :: Python :: 3
Classifier: Programming Language :: Python :: 3.10
Classifier: Programming Language :: Python :: 3.11
Classifier: Programming Language :: Python :: 3.12
Classifier: Topic :: Home Automation
Requires-Dist: bitstruct (>=8.19.0,<9.0.0)
Requires-Dist: bleak (>=0.21.1,<0.22.0)
Requires-Dist: bleak-retry-connector (>=3.4.0,<4.0.0)
Requires-Dist: ruff (>=0.3.5,<0.4.0)
Project-URL: Repository, https://github.com/blitzkopf/shadeorb
